Metadata-Version: 2.1
Name: trendet
Version: 0.6
Summary: trendet - Trend detection on stock time series data
Home-page: https://github.com/alvarobartt/trendet
Author: Alvaro Bartolome
Author-email: alvarob96@usal.es
License: MIT License
Download-URL: https://github.com/alvarobartt/trendet/archive/0.6.tar.gz
Project-URL: Bug Reports, https://github.com/alvarobartt/trendet/issues
Project-URL: Source, https://github.com/alvarobartt/trendet
Project-URL: Documentation, https://trendet.readthedocs.io/
Keywords: trend detection,stock analysis,stock,trend analysis
Platform: UNKNOWN
Classifier: Development Status :: 4 - Beta
Classifier: Programming Language :: Python :: 3 :: Only
Classifier: Programming Language :: Python :: 3.6
Classifier: Programming Language :: Python :: 3.7
Classifier: Programming Language :: Python :: 3.8
Classifier: License :: OSI Approved :: MIT License
Classifier: Intended Audience :: Developers
Classifier: Topic :: Office/Business :: Financial
Classifier: Topic :: Office/Business :: Financial :: Investment
Classifier: Topic :: Scientific/Engineering :: Information Analysis
Classifier: Topic :: Software Development :: Libraries
Requires-Python: >=3
